LICENSE.txt
MANIFEST.in
README.md
setup.py
SqlHBase.egg-info/PKG-INFO
SqlHBase.egg-info/SOURCES.txt
SqlHBase.egg-info/dependency_links.txt
SqlHBase.egg-info/requires.txt
SqlHBase.egg-info/top_level.txt
bin/sqlhbase-mysqlimport
bin/sqlhbase-populate
sqlhbase/__init__.py
sqlhbase/hive.py
sqlhbase/intake.py
sqlhbase/mysql.py
sqlhbase/populate.py
sqlhbase/rowvalue.py
sqlhbase/borgs/__init__.py
sqlhbase/borgs/hbase.py
sqlhbase/borgs/hive.py
sqlhbase/merge/__init__.py
sqlhbase/merge/diff.py
sqlhbase/merge/stone.py
sqlhbase/test/test_thrift.py