Metadata-Version: 1.0
Name: SqlHBase
Version: 0.4
Summary: MySQLDump to HBase, ETL scripts
Home-page: http://www.rocket-internet.de
Author: Guido Serra aka Zeph
Author-email: zeph@fsfe.org
License: GPL 3
Platform: UNKNOWN
